{
  "$schema": "../frontend/node_modules/@tauri-apps/cli/config.schema.json",
  "productName": "Flick",
  "version": "0.1.0",
  "identifier": "io.github.zhy2006.flick",
  "build": {
    "beforeDevCommand": "npm run dev -- --port 1420 --strictPort",
    "beforeBuildCommand": "npm run build",
    "devUrl": "http://localhost:1420",
    "frontendDist": "../dist"
  },
  "app": {
    "macOSPrivateApi": true,
    "withGlobalTauri": false,
    "windows": [],
    "security": {
      "csp": null
    }
  },
  "bundle": {
    "active": true,
    "resources": [
      "resources/ocr/onnx/**/*",
      "icons/trayTemplate.png",
      "icons/trayTemplate@2x.png"
    ],
    "icon": [
      "icons/icon.icns",
      "icons/icon.ico",
      "icons/icon.png",
      "icons/icon_32x32.png",
      "icons/icon_128x128.png",
      "icons/icon_128x128@2x.png",
      "icons/icon_256x256.png",
      "icons/icon_256x256@2x.png",
      "icons/icon_512x512.png",
      "icons/icon_512x512@2x.png"
    ],
    "targets": ["dmg"],
    "createUpdaterArtifacts": false,
    "macOS": {
      "minimumSystemVersion": "11.0"
    }
  }
}
